keckdrpframework/__init__.py
keckdrpframework/config/__init__.py
keckdrpframework/config/framework_config.py
keckdrpframework/core/__init__.py
keckdrpframework/core/framework.py
keckdrpframework/core/queues.py
keckdrpframework/core/server_task.py
keckdrpframework/extern/__init__.py
keckdrpframework/models/__init__.py
keckdrpframework/models/action.py
keckdrpframework/models/arguments.py
keckdrpframework/models/data_set.py
keckdrpframework/models/event.py
keckdrpframework/models/processing_context.py
keckdrpframework/mytests/__init__.py
keckdrpframework/mytests/example.py
keckdrpframework/pipelines/__init__.py
keckdrpframework/pipelines/base_pipeline.py
keckdrpframework/primitives/__init__.py
keckdrpframework/primitives/base_img.py
keckdrpframework/primitives/base_primitive.py
keckdrpframework/primitives/ccd_primitives.py
keckdrpframework/primitives/create_contact_sheet_HTML.py
keckdrpframework/primitives/hist_equal2d.py
keckdrpframework/primitives/ingest_files.py
keckdrpframework/primitives/noise_removal.py
keckdrpframework/primitives/save_png.py
keckdrpframework/primitives/simple_fits_reader.py
keckdrpframework/primitives/template.py
keckdrpframework/tools/__init__.py
keckdrpframework/tools/add_event.py
keckdrpframework/tools/event_queue_info.py
keckdrpframework/tools/interface.py
keckdrpframework/tools/start_queue_manager.py
keckdrpframework/tools/stop_queue_manager.py
keckdrpframework/utils/__init__.py
keckdrpframework/utils/drpf_logger.py
keckdrpframework/utils/easy_http.py
keckdrpframework/utils/try_wrapper.py
keckdrpframework-0.1.dev0.dist-info/METADATA
keckdrpframework-0.1.dev0.dist-info/WHEEL
keckdrpframework-0.1.dev0.dist-info/entry_points.txt
keckdrpframework-0.1.dev0.dist-info/top_level.txt
keckdrpframework-0.1.dev0.dist-info/RECORD
