Metadata-Version: 2.1
Name: keckdrpframework
Version: 0.1.dev0
Summary: Framework for DRPs at Keck
Home-page: https://github.com/Keck-DataReductionPipelines/KeckDRPFramework.git
Author: L. Rizzi, S. Kwok, M. Brown
Author-email: lrizzi@keck.hawaii.edu
License: BSD 3-Clause
Platform: UNKNOWN
Provides: k
Provides: e
Provides: c
Provides: k
Provides: d
Provides: r
Provides: p
Provides: f
Provides: r
Provides: a
Provides: m
Provides: e
Provides: w
Provides: o
Provides: r
Provides: k
Requires-Dist: astropy
